{
    "sigla": "RN",
    "nome": "Rio Grande do Norte",
    "ibge" : 24,
    "cidades": [
        {"uf":"RN","name":"Acari", "ibge":"00109"},
        {"uf":"RN","name":"Açu", "ibge":"00208"},
        {"uf":"RN","name":"Afonso Bezerra", "ibge":"00307"},
        {"uf":"RN","name":"Água Nova", "ibge":"00406"},
        {"uf":"RN","name":"Alexandria", "ibge":"00505"},
        {"uf":"RN","name":"Almino Afonso", "ibge":"00604"},
        {"uf":"RN","name":"Alto do Rodrigues", "ibge":"00703"},
        {"uf":"RN","name":"Angicos", "ibge":"00802"},
        {"uf":"RN","name":"Antônio Martins", "ibge":"00901"},
        {"uf":"RN","name":"Apodi", "ibge":"01008"},
        {"uf":"RN","name":"Areia Branca", "ibge":"01107"},
        {"uf":"RN","name":"Arês", "ibge":"01206"},
        {"uf":"RN","name":"Augusto Severo", "ibge":"01305"},
        {"uf":"RN","name":"Baía Formosa", "ibge":"01404"},
        {"uf":"RN","name":"Baraúna", "ibge":"01453"},
        {"uf":"RN","name":"Barcelona", "ibge":"01503"},
        {"uf":"RN","name":"Bento Fernandes", "ibge":"01602"},
        {"uf":"RN","name":"Bodó", "ibge":"01651"},
        {"uf":"RN","name":"Bom Jesus", "ibge":"01701"},
        {"uf":"RN","name":"Brejinho", "ibge":"01800"},
        {"uf":"RN","name":"Caiçara do Norte", "ibge":"01859"},
        {"uf":"RN","name":"Caiçara do Rio do Vento", "ibge":"01909"},
        {"uf":"RN","name":"Caicó", "ibge":"02006"},
        {"uf":"RN","name":"Campo Redondo", "ibge":"02105"},
        {"uf":"RN","name":"Canguaretama", "ibge":"02204"},
        {"uf":"RN","name":"Caraúbas", "ibge":"02303"},
        {"uf":"RN","name":"Carnaúba dos Dantas", "ibge":"02402"},
        {"uf":"RN","name":"Carnaubais", "ibge":"02501"},
        {"uf":"RN","name":"Ceará-Mirim", "ibge":"02600"},
        {"uf":"RN","name":"Cerro Corá", "ibge":"02709"},
        {"uf":"RN","name":"Coronel Ezequiel", "ibge":"02808"},
        {"uf":"RN","name":"Coronel João Pessoa", "ibge":"02907"},
        {"uf":"RN","name":"Cruzeta", "ibge":"03004"},
        {"uf":"RN","name":"Currais Novos", "ibge":"03103"},
        {"uf":"RN","name":"Doutor Severiano", "ibge":"03202"},
        {"uf":"RN","name":"Encanto", "ibge":"03301"},
        {"uf":"RN","name":"Equador", "ibge":"03400"},
        {"uf":"RN","name":"Espírito Santo", "ibge":"03509"},
        {"uf":"RN","name":"Extremoz", "ibge":"03608"},
        {"uf":"RN","name":"Felipe Guerra", "ibge":"03707"},
        {"uf":"RN","name":"Fernando Pedroza", "ibge":"03756"},
        {"uf":"RN","name":"Florânia", "ibge":"03806"},
        {"uf":"RN","name":"Francisco Dantas", "ibge":"03905"},
        {"uf":"RN","name":"Frutuoso Gomes", "ibge":"04002"},
        {"uf":"RN","name":"Galinhos", "ibge":"04101"},
        {"uf":"RN","name":"Goianinha", "ibge":"04200"},
        {"uf":"RN","name":"Governador Dix-Sept Rosado", "ibge":"04309"},
        {"uf":"RN","name":"Grossos", "ibge":"04408"},
        {"uf":"RN","name":"Guamaré", "ibge":"04507"},
        {"uf":"RN","name":"Ielmo Marinho", "ibge":"04606"},
        {"uf":"RN","name":"Ipanguaçu", "ibge":"04705"},
        {"uf":"RN","name":"Ipueira", "ibge":"04804"},
        {"uf":"RN","name":"Itajá", "ibge":"04853"},
        {"uf":"RN","name":"Itaú", "ibge":"04903"},
        {"uf":"RN","name":"Jaçanã", "ibge":"05009"},
        {"uf":"RN","name":"Jandaíra", "ibge":"05108"},
        {"uf":"RN","name":"Janduís", "ibge":"05207"},
        {"uf":"RN","name":"Januário Cicco", "ibge":"05306"},
        {"uf":"RN","name":"Japi", "ibge":"05405"},
        {"uf":"RN","name":"Jardim de Angicos", "ibge":"05504"},
        {"uf":"RN","name":"Jardim de Piranhas", "ibge":"05603"},
        {"uf":"RN","name":"Jardim do Seridó", "ibge":"05702"},
        {"uf":"RN","name":"João Câmara", "ibge":"05801"},
        {"uf":"RN","name":"João Dias", "ibge":"05900"},
        {"uf":"RN","name":"José da Penha", "ibge":"06007"},
        {"uf":"RN","name":"Jucurutu", "ibge":"06106"},
        {"uf":"RN","name":"Jundiá", "ibge":"06155"},
        {"uf":"RN","name":"Lagoa d'Anta", "ibge":"06205"},
        {"uf":"RN","name":"Lagoa de Pedras", "ibge":"06304"},
        {"uf":"RN","name":"Lagoa de Velhos", "ibge":"06403"},
        {"uf":"RN","name":"Lagoa Nova", "ibge":"06502"},
        {"uf":"RN","name":"Lagoa Salgada", "ibge":"06601"},
        {"uf":"RN","name":"Lajes", "ibge":"06700"},
        {"uf":"RN","name":"Lajes Pintadas", "ibge":"06809"},
        {"uf":"RN","name":"Lucrécia", "ibge":"06908"},
        {"uf":"RN","name":"Luís Gomes", "ibge":"07005"},
        {"uf":"RN","name":"Macaíba", "ibge":"07104"},
        {"uf":"RN","name":"Macau", "ibge":"07203"},
        {"uf":"RN","name":"Major Sales", "ibge":"07252"},
        {"uf":"RN","name":"Marcelino Vieira", "ibge":"07302"},
        {"uf":"RN","name":"Martins", "ibge":"07401"},
        {"uf":"RN","name":"Maxaranguape", "ibge":"07500"},
        {"uf":"RN","name":"Messias Targino", "ibge":"07609"},
        {"uf":"RN","name":"Montanhas", "ibge":"07708"},
        {"uf":"RN","name":"Monte Alegre", "ibge":"07807"},
        {"uf":"RN","name":"Monte das Gameleiras", "ibge":"07906"},
        {"uf":"RN","name":"Mossoró", "ibge":"08003"},
        {"uf":"RN","name":"Natal", "ibge":"08102"},
        {"uf":"RN","name":"Nísia Floresta", "ibge":"08201"},
        {"uf":"RN","name":"Nova Cruz", "ibge":"08300"},
        {"uf":"RN","name":"Olho-d'Água do Borges", "ibge":"08409"},
        {"uf":"RN","name":"Ouro Branco", "ibge":"08508"},
        {"uf":"RN","name":"Paraná", "ibge":"08607"},
        {"uf":"RN","name":"Paraú", "ibge":"08706"},
        {"uf":"RN","name":"Parazinho", "ibge":"08805"},
        {"uf":"RN","name":"Parelhas", "ibge":"08904"},
        {"uf":"RN","name":"Parnamirim", "ibge":"03251"},
        {"uf":"RN","name":"Passa e Fica", "ibge":"09100"},
        {"uf":"RN","name":"Passagem", "ibge":"09209"},
        {"uf":"RN","name":"Patu", "ibge":"09308"},
        {"uf":"RN","name":"Pau dos Ferros", "ibge":"09407"},
        {"uf":"RN","name":"Pedra Grande", "ibge":"09506"},
        {"uf":"RN","name":"Pedra Preta", "ibge":"09605"},
        {"uf":"RN","name":"Pedro Avelino", "ibge":"09704"},
        {"uf":"RN","name":"Pedro Velho", "ibge":"09803"},
        {"uf":"RN","name":"Pendências", "ibge":"09902"},
        {"uf":"RN","name":"Pilões", "ibge":"10009"},
        {"uf":"RN","name":"Poço Branco", "ibge":"10108"},
        {"uf":"RN","name":"Portalegre", "ibge":"10207"},
        {"uf":"RN","name":"Porto do Mangue", "ibge":"10256"},
        {"uf":"RN","name":"Presidente Juscelino", "ibge":"10306"},
        {"uf":"RN","name":"Pureza", "ibge":"10405"},
        {"uf":"RN","name":"Rafael Fernandes", "ibge":"10504"},
        {"uf":"RN","name":"Rafael Godeiro", "ibge":"10603"},
        {"uf":"RN","name":"Riacho da Cruz", "ibge":"10702"},
        {"uf":"RN","name":"Riacho de Santana", "ibge":"10801"},
        {"uf":"RN","name":"Riachuelo", "ibge":"10900"},
        {"uf":"RN","name":"Rio do Fogo", "ibge":"08953"},
        {"uf":"RN","name":"Rodolfo Fernandes", "ibge":"11007"},
        {"uf":"RN","name":"Ruy Barbosa", "ibge":"11106"},
        {"uf":"RN","name":"Santa Cruz", "ibge":"11205"},
        {"uf":"RN","name":"Santa Maria", "ibge":"09332"},
        {"uf":"RN","name":"Santana do Matos", "ibge":"11403"},
        {"uf":"RN","name":"Santana do Seridó", "ibge":"11429"},
        {"uf":"RN","name":"Santo Antônio", "ibge":"11502"},
        {"uf":"RN","name":"São Bento do Norte", "ibge":"11601"},
        {"uf":"RN","name":"São Bento do Trairí", "ibge":"11700"},
        {"uf":"RN","name":"São Fernando", "ibge":"11809"},
        {"uf":"RN","name":"São Francisco do Oeste", "ibge":"11908"},
        {"uf":"RN","name":"São Gonçalo do Amarante", "ibge":"12005"},
        {"uf":"RN","name":"São João do Sabugi", "ibge":"12104"},
        {"uf":"RN","name":"São José de Mipibu", "ibge":"12203"},
        {"uf":"RN","name":"São José do Campestre", "ibge":"12302"},
        {"uf":"RN","name":"São José do Seridó", "ibge":"12401"},
        {"uf":"RN","name":"São Miguel", "ibge":"12500"},
        {"uf":"RN","name":"São Miguel de Touros", "ibge":"12559"},
        {"uf":"RN","name":"São Paulo do Potengi", "ibge":"12609"},
        {"uf":"RN","name":"São Pedro", "ibge":"12708"},
        {"uf":"RN","name":"São Rafael", "ibge":"12807"},
        {"uf":"RN","name":"São Tomé", "ibge":"12906"},
        {"uf":"RN","name":"São Vicente", "ibge":"13003"},
        {"uf":"RN","name":"Senador Elói de Souza", "ibge":"13102"},
        {"uf":"RN","name":"Senador Georgino Avelino", "ibge":"13201"},
        {"uf":"RN","name":"Serra de São Bento", "ibge":"13300"},
        {"uf":"RN","name":"Serra do Mel", "ibge":"13359"},
        {"uf":"RN","name":"Serra Negra do Norte", "ibge":"13409"},
        {"uf":"RN","name":"Serrinha", "ibge":"13508"},
        {"uf":"RN","name":"Serrinha dos Pintos", "ibge":"13557"},
        {"uf":"RN","name":"Severiano Melo", "ibge":"13607"},
        {"uf":"RN","name":"Sítio Novo", "ibge":"13706"},
        {"uf":"RN","name":"Taboleiro Grande", "ibge":"13805"},
        {"uf":"RN","name":"Taipu", "ibge":"13904"},
        {"uf":"RN","name":"Tangará", "ibge":"14001"},
        {"uf":"RN","name":"Tenente Ananias", "ibge":"14100"},
        {"uf":"RN","name":"Tenente Laurentino Cruz", "ibge":"14159"},
        {"uf":"RN","name":"Tibau", "ibge":"11056"},
        {"uf":"RN","name":"Tibau do Sul", "ibge":"14209"},
        {"uf":"RN","name":"Timbaúba dos Batistas", "ibge":"14308"},
        {"uf":"RN","name":"Touros", "ibge":"14407"},
        {"uf":"RN","name":"Triunfo Potiguar", "ibge":"14456"},
        {"uf":"RN","name":"Umarizal", "ibge":"14506"},
        {"uf":"RN","name":"Upanema", "ibge":"14605"},
        {"uf":"RN","name":"Várzea", "ibge":"14704"},
        {"uf":"RN","name":"Venha-Ver", "ibge":"14753"},
        {"uf":"RN","name":"Vera Cruz", "ibge":"14803"},
        {"uf":"RN","name":"Viçosa", "ibge":"14902"},
        {"uf":"RN","name":"Vila Flor", "ibge":"15008"}
    ]
}